Workbook

Sheet Financial Analysis
A1: Initial Investment | B1: Cost Estimate (INR) | C1: Revenue Projections | D1: Expected Revenue (INR) | E1: Operational Expenses | F1: Cost Estimate per Year (INR)
A2: Land Costs | B2: 50000000 | C2: Total Revenue (Year 1) | D2: =C22 -> 15000000 | E2: Labor | F2: 500000
A3: Construction Costs | B3: 15000000 | C3: Total Revenue (Year 2) | D3: =D22 -> 15147000 | E3: Maintenance | F3: 400000
A4: Equipment Costs | B4: 16000000 | C4: Total Revenue (Year 3) | D4: =E22 -> 15372690 | E4: Other Expenses | F4: 500000
A5: Permits & Licenses | B5: 1000000 | C5: Total Revenue (Year 4) | D5: =F22 -> 15601743
A6: Miscellaneous Costs | B6: 1500000 | C6: Total Revenue (Year 5) | D6: =G22 -> 15834209
A7: Total Initial Investment | B7: =SUM(B2:B6) -> 83500000
E9: Total Operating Expenses | F9: =SUM(F2:F8) -> 1400000
A19: Revenue Projections | B19: Year 0 | C19: Year 1 | D19: Year 2 | E19: Year 3 | F19: Year 4 | G19: Year 5
A20: Annual Energy Production(KWh) | B20: 0 | C20: 1500000 | D20: =C20-(C20*1/100) -> 1485000 | E20: =D20-(0.5/100*D20) -> 1477575 | F20: =E20-(0.5/100*E20) -> 1470187.1 | G20: =F20-(0.5/100*F20) -> 1462836.2
A21: Tarrif | B21: 0 | C21: 10 | D21: =C21+2/100*C21 -> 10.2 | E21: =D21+2/100*D21 -> 10.404 | F21: =E21+2/100*E21 -> 10.61208 | G21: =F21+2/100*F21 -> 10.824322
B22: =B20*B21 -> 0 | C22: =C20*C21 -> 15000000 | D22: =D20*D21 -> 15147000 | E22: =E20*E21 -> 15372690 | F22: =F20*F21 -> 15601743 | G22: =G20*G21 -> 15834209
A24: Net Cash Flow | B24: =-B7 -> -83500000 | C24: =C22-$F$9 -> 13600000 | D24: =D22-$F$9 -> 13747000 | E24: =E22-$F$9 -> 13972690 | F24: =F22-$F$9 -> 14201743 | G24: =G22-$F$9 -> 14434209

Sheet NPV Calculation
A1: Year | B1: Net Cash Flow (INR) | C1: Present Value of Cash Flow
A2: 0 | B2: ='Financial Analysis'!B24 -> -83500000 | C2: =(B2/((1+$B$9)^A2)) -> -83500000
A3: 1 | B3: ='Financial Analysis'!C24 -> 13600000 | C3: =(B3/((1+$B$9)^A3)) -> 12142857
A4: 2 | B4: ='Financial Analysis'!D24 -> 13747000 | C4: =(B4/((1+$B$9)^A4)) -> 10959024
A5: 3 | B5: ='Financial Analysis'!E24 -> 13972690 | C5: =(B5/((1+$B$9)^A5)) -> 9945485
A6: 4 | B6: ='Financial Analysis'!F24 -> 14201743 | C6: =(B6/((1+$B$9)^A6)) -> 9025464.7
A7: 5 | B7: ='Financial Analysis'!G24 -> 14434209 | C7: =(B7/((1+$B$9)^A7)) -> 8190358
A9: Discount Factor | B9: 0.12
A11: NPV | B11: =SUM(C2:C7) -> -33236811

Sheet Sensitivity Analysis
A1: Discount Factor Change | B1: Values for the Parameter | C1: NPV | D1: NPV % Change
A2: 20 | B2: =$B$4+(A2*$B$4/100) -> 14.4 | C2: -40117161 | D2: =((C2-$C$4)/$C$4)*100 -> 7.7352221
A3: 10 | B3: =$B$4+(A3*$B$4/100) -> 13.2 | C3: -38711269 | D3: =((C3-$C$4)/$C$4)*100 -> 3.9596795
A4: 0 | B4: 12 | C4: -37236811 | D4: 0
A5: -10 | B5: =$B$4+(A5*$B$4/100) -> 10.8 | C5: -35689358 | D5: =((C5-$C$4)/$C$4)*100 -> -4.1557062
A6: -20 | B6: =$B$4+(A6*$B$4/100) -> 9.6 | C6: -34064134 | D6: =((C6-$C$4)/$C$4)*100 -> -8.520269
A9: Land Prices Change | B9: Value for the Parameter | C9: NPV | D9: NPV % Change
A10: 20 | B10: =$B$12+(A10*$B$12/100) -> 60000000 | C10: -47236811 | D10: =((C10-$C$12)/$C$12)*100 -> 26.855146
A11: 10 | B11: =$B$12+(A11*$B$12/100) -> 55000000 | C11: -42236811 | D11: =((C11-$C$12)/$C$12)*100 -> 13.427573
A12: 0 | B12: 50000000 | C12: -37236811 | D12: =((C12-$C$12)/$C$12)*100 -> 0
A13: -10 | B13: =$B$12+(A13*$B$12/100) -> 45000000 | C13: -32236811 | D13: =((C13-$C$12)/$C$12)*100 -> -13.427573
A14: -20 | B14: =$B$12+(A14*$B$12/100) -> 40000000 | C14: -27236811 | D14: =((C14-$C$12)/$C$12)*100 -> -26.855146
A16: Equipment Cost | B16: Value for the Parameter | C16: NPV | D16: NPV % Change
A17: 20 | B17: =$B$19+(A17*$B$19/100) -> 24000000 | C17: -41236811 | D17: =((C17-$C$19)/$C$19)*100 -> 10.742058
A18: 10 | B18: =$B$19+(A18*$B$19/100) -> 22000000 | C18: -39236811 | D18: =((C18-$C$19)/$C$19)*100 -> 5.3710292
A19: 0 | B19: 20000000 | C19: -37236811 | D19: =((C19-$C$19)/$C$19)*100 -> 0
A20: -10 | B20: =$B$19+(A20*$B$19/100) -> 18000000 | C20: -35236811 | D20: =((C20-$C$19)/$C$19)*100 -> -5.3710292
A21: -20 | B21: =$B$19+(A21*$B$19/100) -> 16000000 | C21: -33236811 | D21: =((C21-$C$19)/$C$19)*100 -> -10.742058
